ice/__init__.py
ice/__version__.py
ice/analysis.py
ice/classes/__init__.py
ice/classes/edit_proposal.py
ice/classes/edit_proposal_creator.py
ice/classes/guide_target.py
ice/classes/ice_result.py
ice/classes/pair_alignment.py
ice/classes/proposal_base.py
ice/classes/sanger_analysis.py
ice/classes/sanger_object.py
ice/outputs/__init__.py
ice/outputs/create_discordance_indel_files.py
ice/outputs/create_json.py
ice/outputs/create_trace_files.py
ice/tests/__init__.py
ice/tests/fixtures.py
ice/tests/test_alignment.py
ice/tests/test_analysis.py
ice/tests/test_batch.py
ice/tests/test_edit_proposal_creator.py
ice/tests/test_sanger_object.py
ice/tests/test_sequence.py
ice/tests/test_utility.py
ice/utility/__init__.py
ice/utility/misc.py
ice/utility/sequence.py
synthego_ice-1.2.0.dist-info/LICENSE
synthego_ice-1.2.0.dist-info/METADATA
synthego_ice-1.2.0.dist-info/WHEEL
synthego_ice-1.2.0.dist-info/entry_points.txt
synthego_ice-1.2.0.dist-info/top_level.txt
synthego_ice-1.2.0.dist-info/RECORD
