Metadata-Version: 2.1
Name: synthego-ice
Version: 1.2.0
Summary: Synthego - Inference of CRISPR Edits (ICE)
Home-page: https://github.com/synthego-open/ice
Author: Synthego
License: UNKNOWN
Keywords: sanger crispr indel genomics
Platform: UNKNOWN
Classifier: Development Status :: 5 - Production/Stable
Classifier: Intended Audience :: Science/Research
Classifier: Topic :: Scientific/Engineering
Classifier: License :: Free for non-commercial use
Classifier: Programming Language :: Python :: 3
Classifier: Programming Language :: Python :: 3.4
Classifier: Programming Language :: Python :: 3.5
Classifier: Programming Language :: Python :: 3.6
Requires-Dist: pytest (==5.2.2)
Requires-Dist: biopython (>=1.70)
Requires-Dist: coverage (>=4.4.1)
Requires-Dist: pytest-cov (==2.5.1)
Requires-Dist: matplotlib (>=2.1.0)
Requires-Dist: numpy (>=1.13.3)
Requires-Dist: pandas (>=0.20.3)
Requires-Dist: scipy (>=0.19.1)
Requires-Dist: sklearn (>=0.0)
Requires-Dist: xlrd (>=1.1.0)
Requires-Dist: xlsxwriter (>=1.0.2)
Provides-Extra: test
Requires-Dist: py.test ; extra == 'test'
Requires-Dist: coverage ; extra == 'test'
